{"id":"601","name":"Terror Hunter","tags":"Action,Mystery,Long,Strip,Web,Comic,Full,Color,Monsters,Survival,Villainess","author":"Idol Meow Studio &#40爱豆喵工作室&#41","status":"OnGoing","content":"One day, countless sinister and distorted monsters suddenly appeared in the city. These monsters would attack or distort the minds of ordinary people at night, turning them into demons. The government called these monsters &quotThe Terror&quot. To deal with the terror attacks, and the higher-ups of the government officials and businessmen created a floating city to remotely control the whole world. However, the majority of people still live on the ground, reproducing and working.","pic":"https:\/\/manhuaplus.org\/uploads\/covers\/terror-hunter.jpg"}