{"id":"98","name":"Reincarnator","tags":"Action,Fantasy,Long,Strip,Adaptation,Web,Comic,Full,Color,Isekai,Time,Travel","author":"갯강구","status":"OnGoing","content":"Abyss, an alternate reality created by a bored god, plucks humans from earth and sets them against monsters and each other in a sick gladiator game.Kang Hansoo, one of the last four survivors, is sent back in time twenty years as the last hope for humanity. He teams up with long lost school friends and enemies to relearn skills and arm himself with the knowledge to break the game once and for all.","pic":"https:\/\/manhuaplus.org\/uploads\/covers\/reincarnator.jpg"}